counter_boxes/__init__.py
counter_boxes/counter.py
counter_boxes/export.py
counter_boxes/models/__init__.py
counter_boxes/models/common.py
counter_boxes/models/experimental.py
counter_boxes/models/yolo.py
counter_boxes/utils/__init__.py
counter_boxes/utils/activations.py
counter_boxes/utils/augmentations.py
counter_boxes/utils/autoanchor.py
counter_boxes/utils/autobatch.py
counter_boxes/utils/callbacks.py
counter_boxes/utils/dataloaders.py
counter_boxes/utils/downloads.py
counter_boxes/utils/general.py
counter_boxes/utils/loss.py
counter_boxes/utils/metrics.py
counter_boxes/utils/plots.py
counter_boxes/utils/torch_utils.py
counter_boxes/utils/triton.py
counter_boxes/utils/segment/__init__.py
counter_boxes/utils/segment/augmentations.py
counter_boxes/utils/segment/dataloaders.py
counter_boxes/utils/segment/general.py
counter_boxes/utils/segment/loss.py
counter_boxes/utils/segment/metrics.py
counter_boxes/utils/segment/plots.py
counter_boxes_by_mosa-0.0.5.dist-info/LICENSE
counter_boxes_by_mosa-0.0.5.dist-info/METADATA
counter_boxes_by_mosa-0.0.5.dist-info/WHEEL
counter_boxes_by_mosa-0.0.5.dist-info/top_level.txt
counter_boxes_by_mosa-0.0.5.dist-info/RECORD
